ml_buildkit/__init__.py
ml_buildkit/_about.py
ml_buildkit/_cli.py
ml_buildkit/_utilities.py
ml_buildkit/build_utils.py
ml_buildkit/helpers/__init__.py
ml_buildkit/helpers/build_docker.py
ml_buildkit/helpers/build_mkdocs.py
ml_buildkit/helpers/build_python.py
ml_buildkit/helpers/openapi_utils.py
ml_buildkit-0.6.18.dist-info/LICENSE
ml_buildkit-0.6.18.dist-info/METADATA
ml_buildkit-0.6.18.dist-info/WHEEL
ml_buildkit-0.6.18.dist-info/entry_points.txt
ml_buildkit-0.6.18.dist-info/top_level.txt
ml_buildkit-0.6.18.dist-info/RECORD
